yx/__init__.py
yx-0.0.11.dist-info/licenses/LICENSE
yx-0.0.11.dist-info/METADATA
yx-0.0.11.dist-info/WHEEL
yx-0.0.11.dist-info/top_level.txt
yx-0.0.11.dist-info/RECORD
