Metadata-Version: 2.4
Name: yx
Version: 0.0.11
Summary: Dataframe manipulation tools
Home-page: https://github.com/t-c-w/yx
Author: Thor Whalen
License: apache-2.0
Platform: any
License-File: LICENSE
Requires-Dist: numpy
Requires-Dist: pandas
Dynamic: license-file
